setup.py
fwarp/__init__.py
fwarp/best_warp.py
fwarp/bezier.py
fwarp/canonical.py
fwarp/linear.py
fwarp/spline.py
fwarp/warp.py
fwarp.egg-info/PKG-INFO
fwarp.egg-info/SOURCES.txt
fwarp.egg-info/dependency_links.txt
fwarp.egg-info/top_level.txt
fwarp/test/__init__.py
fwarp/test/canonical_test.py
fwarp/test/warp_test.py