Metadata-Version: 1.0
Name: fwarp
Version: 0.0.16
Summary: Utility for warping functions
Home-page: https://github.com/n-s-f/warp
Author: UNKNOWN
Author-email: UNKNOWN
License: UNKNOWN
Platform: UNKNOWN
